[{"language":"JavaScript","precent":"36.84"},{"language":"PHP","precent":"10.53"},{"language":"HTML","precent":"9.47"},{"language":"Shell","precent":"6.32"},{"language":"Svelte","precent":"6.32"},{"language":"Dockerfile","precent":"5.26"},{"language":"Visual Basic .NET","precent":"4.21"},{"language":"Java","precent":"3.16"},{"language":"Python","precent":"3.16"},{"language":"TypeScript","precent":"3.16"},{"language":"C","precent":"1.05"},{"language":"CSS","precent":"1.05"},{"language":"Smarty","precent":"1.05"},{"language":"Vue","precent":"1.05"},{"language":"JavaScript","precent":"205.88"},{"language":"PHP","precent":"58.82"},{"language":"HTML","precent":"52.94"},{"language":"Shell","precent":"35.29"},{"language":"Svelte","precent":"35.29"},{"language":"Dockerfile","precent":"29.41"},{"language":"Visual Basic .NET","precent":"23.53"},{"language":"Java","precent":"17.65"},{"language":"Python","precent":"17.65"},{"language":"TypeScript","precent":"17.65"},{"language":"C","precent":"5.88"},{"language":"CSS","precent":"5.88"},{"language":"Smarty","precent":"5.88"},{"language":"Vue","precent":"5.88"}]